{ "predictions" : [ { "description" : "Victorville, CA, EUA", "matched_substrings" : [ { "length" : 4, "offset" : 0 } ], "place_id" : "ChIJedLdY1pkw4ARdjT0JVkRlQ0", "reference" : "ChIJedLdY1pkw4ARdjT0JVkRlQ0", "structured_formatting" : { "main_text" : "Victorville", "main_text_matched_substrings" : [ { "length" : 4, "offset" : 0 } ], "secondary_text" : "CA, EUA" }, "terms" : [ { "offset" : 0, "value" : "Victorville" }, { "offset" : 13, "value" : "CA" }, { "offset" : 17, "value" : "EUA" } ], "types" : [ "locality", "political", "geocode" ] }, { "description" : "Victoria, TX, EUA", "matched_substrings" : [ { "length" : 4, "offset" : 0 } ], "place_id" : "ChIJO6wtLttmQoYRfSZjb1YN4u4", "reference" : "ChIJO6wtLttmQoYRfSZjb1YN4u4", "structured_formatting" : { "main_text" : "Victoria", "main_text_matched_substrings" : [ { "length" : 4, "offset" : 0 } ], "secondary_text" : "TX, EUA" }, "terms" : [ { "offset" : 0, "value" : "Victoria" }, { "offset" : 10, "value" : "TX" }, { "offset" : 14, "value" : "EUA" } ], "types" : [ "locality", "political", "geocode" ] }, { "description" : "Victor, NY, EUA", "matched_substrings" : [ { "length" : 4, "offset" : 0 } ], "place_id" : "ChIJq56InDUw0YkRVNXyEiGo85M", "reference" : "ChIJq56InDUw0YkRVNXyEiGo85M", "structured_formatting" : { "main_text" : "Victor", "main_text_matched_substrings" : [ { "length" : 4, "offset" : 0 } ], "secondary_text" : "NY, EUA" }, "terms" : [ { "offset" : 0, "value" : "Victor" }, { "offset" : 8, "value" : "NY" }, { "offset" : 12, "value" : "EUA" } ], "types" : [ "locality", "political", "geocode" ] }, { "description" : "Victoria, VA, EUA", "matched_substrings" : [ { "length" : 4, "offset" : 0 } ], "place_id" : "ChIJ9UzddEEUsokRGM1qOaLu338", "reference" : "ChIJ9UzddEEUsokRGM1qOaLu338", "structured_formatting" : { "main_text" : "Victoria", "main_text_matched_substrings" : [ { "length" : 4, "offset" : 0 } ], "secondary_text" : "VA, EUA" }, "terms" : [ { "offset" : 0, "value" : "Victoria" }, { "offset" : 10, "value" : "VA" }, { "offset" : 14, "value" : "EUA" } ], "types" : [ "locality", "political", "geocode" ] }, { "description" : "Victoriaville, Quebec, Canadá", "matched_substrings" : [ { "length" : 4, "offset" : 0 } ], "place_id" : "ChIJNykTamsBuEwRgDRNrq0MBAU", "reference" : "ChIJNykTamsBuEwRgDRNrq0MBAU", "structured_formatting" : { "main_text" : "Victoriaville", "main_text_matched_substrings" : [ { "length" : 4, "offset" : 0 } ], "secondary_text" : "Quebec, Canadá" }, "terms" : [ { "offset" : 0, "value" : "Victoriaville" }, { "offset" : 15, "value" : "Quebec" }, { "offset" : 23, "value" : "Canadá" } ], "types" : [ "locality", "political", "geocode" ] } ], "status" : "OK" }